ioc_engine/__init__.py
ioc_engine/application_context.py
ioc_engine/exception.py
ioc_engine/function_util.py
ioc_engine/ioc_engine.py
ioc_engine/module_util.py
ioc_engine-0.0.4.dist-info/METADATA
ioc_engine-0.0.4.dist-info/WHEEL
ioc_engine-0.0.4.dist-info/top_level.txt
ioc_engine-0.0.4.dist-info/RECORD
