Metadata-Version: 2.1
Name: ioc-engine
Version: 0.0.4
Summary: ioc容器
Home-page: 
Author: dawndevil
Author-email: 351987551@qq.com
Classifier: Programming Language :: Python :: 3
Classifier: License :: OSI Approved :: MIT License
Classifier: Operating System :: OS Independent
